{
  "id": "snapshot_1762366336204_2h9yloxkq",
  "approvalId": "approval_1762366336190_6a6mhesw4",
  "approvalTitle": "批准Emby服务器管理平台任务分解文档",
  "version": 1,
  "timestamp": "2025-11-05T18:12:16.204Z",
  "trigger": "initial",
  "status": "pending",
  "content": "# Tasks Document - Emby服务器管理平台\n\n## 后端开发任务\n\n- [ ] 1. 完善用户认证系统\n  - File: backend/internal/services/auth.go\n  - 实现登录、注册、令牌刷新完整逻辑\n  - 添加密码强度验证和账户锁定机制\n  - Purpose: 提供安全的用户认证服务\n  - _Leverage: backend/pkg/auth/jwt.go, backend/internal/models/models.go_\n  - _Requirements: Requirement 2 - 用户认证和权限管理_\n  - _Prompt: Role: Backend Security Developer specializing in authentication and authorization systems | Task: Implement comprehensive authentication service including login, registration, token refresh, password validation, and account lockout mechanisms following Requirement 2, leveraging existing JWT utilities and user models | Restrictions: Must use bcrypt with cost factor >=12, implement rate limiting, follow security best practices, maintain backward compatibility | Success: Authentication service is secure, handles edge cases, password policies enforced, account lockout works correctly_\n\n- [ ] 2. 实现用户仓储层\n  - File: backend/internal/repositories/user.go\n  - 创建用户CRUD操作和查询方法\n  - 添加用户搜索和分页功能\n  - Purpose: 提供用户数据访问层\n  - _Leverage: backend/pkg/database/database.go, backend/internal/models/models.go_\n  - _Requirements: Requirement 2 - 用户认证和权限管理_\n  - _Prompt: Role: Backend Database Developer with GORM and PostgreSQL expertise | Task: Implement comprehensive user repository with CRUD operations, search functionality, and pagination following Requirement 2, using existing database connection and user models | Restrictions: Must use GORM properly, handle database errors gracefully, validate inputs, maintain transaction integrity | Success: Repository handles all user operations efficiently, database queries optimized, error handling comprehensive_\n\n- [ ] 3. 创建Emby服务器管理服务\n  - File: backend/internal/services/emby.go\n  - 实现服务器添加、连接测试、状态监控\n  - 创建Emby API客户端和重试机制\n  - Purpose: 管理多个Emby服务器连接\n  - _Leverage: backend/internal/models/models.go, backend/pkg/database/database.go_\n  - _Requirements: Requirement 1 - 多服务器连接管理_\n  - _Prompt: Role: Integration Developer with expertise in API clients and external service integration | Task: Create comprehensive Emby server management service including server registration, connection testing, status monitoring, and API client implementation following Requirement 1, leveraging existing server models and database layer | Restrictions: Must handle API timeouts, implement retry logic with exponential backoff, validate server responses, maintain connection state | Success: Service reliably manages multiple Emby servers, handles connection failures gracefully, provides accurate status monitoring_\n\n- [ ] 4. 创建Emby API客户端\n  - File: backend/pkg/emby/client.go\n  - 实现标准化的Emby API请求包装\n  - 处理认证、错误处理、响应解析\n  - Purpose: 统一Emby API调用接口\n  - _Leverage: Go HTTP客户端, JWT认证机制_\n  - _Requirements: Requirement 1 - 多服务器连接管理, Requirement 3 - 跨服务器媒体库管理, Requirement 4 - 远程播放控制_\n  - _Prompt: Role: API Integration Specialist with experience in HTTP clients and RESTful APIs | Task: Create robust Emby API client with authentication, error handling, response parsing, and rate limiting supporting server management, media library operations, and playback control following Requirements 1, 3, and 4 | Restrictions: Must handle HTTP errors, respect rate limits, parse all response formats, maintain connection pooling | Success: API client works reliably with all Emby API endpoints, handles authentication correctly, provides comprehensive error reporting_\n\n- [ ] 5. 实现媒体库聚合服务\n  - File: backend/internal/services/media.go\n  - 创建跨服务器媒体库搜索和同步\n  - 实现媒体元数据缓存机制\n  - Purpose: 聚合和缓存跨服务器媒体信息\n  - _Leverage: backend/pkg/emby/client.go, backend/internal/models/models.go_\n  - _Requirements: Requirement 3 - 跨服务器媒体库管理_\n  - _Prompt: Role: Data Aggregation Specialist with expertise in caching, search algorithms, and data synchronization | Task: Implement media aggregation service supporting cross-server library browsing, search functionality, and metadata caching following Requirement 3, using Emby API client and existing media models | Restrictions: Must handle large datasets efficiently, implement smart caching strategies, support real-time updates, maintain data consistency | Success: Media aggregation provides fast cross-server search, maintains up-to-date metadata, handles cache invalidation correctly_\n\n- [ ] 6. 实现播放控制服务\n  - File: backend/internal/services/playback.go\n  - 创建远程播放控制指令处理\n  - 实现播放进度同步和记录\n  - Purpose: 管理跨设备播放控制和同步\n  - _Leverage: backend/pkg/emby/client.go, backend/internal/models/models.go_\n  - _Requirements: Requirement 4 - 远程播放控制_\n  - _Prompt: Role: Real-time Systems Developer with expertise in WebSocket, messaging, and state synchronization | Task: Create playback control service supporting remote commands, progress synchronization, and multi-device session management following Requirement 4, using Emby API client and playback models | Restrictions: Must handle concurrent sessions, maintain state consistency, support real-time updates, handle device disconnections | Success: Playback control works across all devices, progress sync is accurate, handles network interruptions gracefully_\n\n- [ ] 7. 实现设备管理服务\n  - File: backend/internal/services/device.go\n  - 创建设备注册、状态监控、会话管理\n  - 实现设备自动清理和异常检测\n  - Purpose: 管理连接设备和会话状态\n  - _Leverage: backend/internal/models/models.go, backend/pkg/database/database.go_\n  - _Requirements: Requirement 5 - 设备管理和状态监控_\n  - _Prompt: Role: Device Management Specialist with expertise in session handling and monitoring systems | Task: Create device management service supporting registration, status monitoring, session management, and cleanup following Requirement 5, using existing device models and database layer | Restrictions: Must handle device lifecycle properly, detect anomalies, maintain session security, optimize resource usage | Success: Device management tracks all connected devices accurately, detects issues promptly, manages sessions securely_\n\n- [ ] 8. 创建WebSocket实时通信\n  - File: backend/internal/websocket/hub.go\n  - 实现服务器状态推送和实时更新\n  - 处理设备状态变化和播放进度同步\n  - Purpose: 提供实时状态更新和通知\n  - _Leverage: Gorilla WebSocket, Redis Pub/Sub_\n  - _Requirements: Requirement 4 - 远程播放控制, Requirement 5 - 设备管理和状态监控_\n  - _Prompt: Role: Real-time Communications Developer with WebSocket and messaging system expertise | Task: Implement WebSocket hub for real-time updates including server status, device monitoring, and playback synchronization following Requirements 4 and 5, using Gorilla WebSocket and Redis | Restrictions: Must handle concurrent connections, message ordering, connection failures, scale horizontally | Success: WebSocket system provides reliable real-time updates, handles connection drops gracefully, supports high concurrent users_\n\n- [ ] 9. 完善API路由和中间件\n  - File: backend/cmd/server/routes/\n  - 创建RESTful API端点和路由\n  - 实现权限检查和参数验证中间件\n  - Purpose: 提供完整的HTTP API接口\n  - _Leverage: backend/internal/middleware/middleware.go, backend/internal/handlers/handlers.go_\n  - _Requirements: All requirements API endpoints_\n  - _Prompt: Role: API Architect with expertise in RESTful design and middleware systems | Task: Create comprehensive RESTful API routes and middleware for all platform features, improving existing handler structure and adding proper validation following all requirements | Restrictions: Must follow REST conventions, implement proper HTTP status codes, validate all inputs, maintain API consistency | Success: API provides complete platform functionality, is well-documented, handles errors properly, maintains security standards_\n\n- [ ] 10. 添加API文档和验证\n  - File: backend/cmd/server/docs/\n  - 完善Swagger文档和API规范\n  - 添加API请求/响应示例\n  - Purpose: 提供完整的API文档\n  - _Leverage: Swagger/OpenAPI工具, Gin Swagger集成_\n  - _Requirements: All requirements documentation_\n  - _Prompt: Role: Technical Writer with API documentation expertise | Task: Create comprehensive Swagger/OpenAPI documentation with examples, schemas, and usage guides for all API endpoints following platform requirements | Restrictions: Must document all endpoints accurately, provide clear examples, maintain documentation synchronization with code | Success: API documentation is complete, accurate, and developer-friendly_\n\n## 前端开发任务\n\n- [ ] 11. 完善用户认证界面\n  - File: frontend/src/views/Login.vue, frontend/src/views/Register.vue\n  - 实现登录、注册、密码重置界面\n  - 添加表单验证和错误提示\n  - Purpose: 提供完整的用户认证界面\n  - _Leverage: frontend/src/stores/user.ts, Frontend/src/services/request.ts_\n  - _Requirements: Requirement 2 - 用户认证和权限管理_\n  - _Prompt: Role: Frontend UI Developer with Vue3 and Element Plus expertise | Task: Create complete authentication interface including login, registration, password reset with form validation and error handling following Requirement 2, using existing user store and request services | Restrictions: Must follow Vue3 composition API patterns, handle all edge cases, ensure accessibility, maintain responsive design | Success: Authentication interface is user-friendly, handles all scenarios properly, provides clear feedback, is fully responsive_\n\n- [ ] 12. 完善用户状态管理\n  - File: frontend/src/stores/user.ts, frontend/src/stores/auth.ts\n  - 实现令牌自动刷新和过期处理\n  - 添加权限检查和角色管理\n  - Purpose: 管理全局认证状态\n  - _Leverage: frontend/src/services/request.ts, Pinia状态管理_\n  - _Requirements: Requirement 2 - 用户认证和权限管理_\n  - _Prompt: Role: Frontend State Management Specialist with Pinia and Vue3 expertise | Task: Implement comprehensive user state management including token refresh, expiration handling, permission checking, and role management following Requirement 2, using existing request services | Restrictions: Must handle token lifecycle properly, maintain state consistency, implement proper error handling, support concurrent tabs | Success: User state management works seamlessly, handles token refresh automatically, maintains security standards_\n\n- [ ] 13. 创建服务器管理界面\n  - File: frontend/src/views/servers/\n  - 实现服务器列表、添加、编辑、测试连接\n  - 添加服务器状态监控和实时更新\n  - Purpose: 提供Emby服务器管理界面\n  - _Leverage: frontend/src/views/Dashboard.vue, Element Plus组件库_\n  - _Requirements: Requirement 1 - 多服务器连接管理_\n  - _Prompt: Role: Frontend Dashboard Developer with complex UI management expertise | Task: Create comprehensive server management interface including list view, add/edit forms, connection testing, and real-time status monitoring following Requirement 1, using dashboard patterns and Element Plus | Restrictions: Must handle async operations properly, provide real-time updates, validate inputs, maintain usability | Success: Server management interface is intuitive, handles all server operations, provides clear status information_\n\n- [ ] 14. 创建媒体库浏览界面\n  - File: frontend/src/views/media/\n  - 实现跨服务器媒体库展示和搜索\n  - 添加媒体详情页和播放控制\n  - Purpose: 提供媒体浏览和搜索界面\n  - _Leverage: frontend/src/components/, 媒体卡片组件_\n  - _Requirements: Requirement 3 - 跨服务器媒体库管理_\n  - _Prompt: Role: Frontend Media UI Developer with gallery and search interface expertise | Task: Create media browsing interface with cross-server library display, advanced search, filtering, and media detail pages following Requirement 3, using existing component patterns | Restrictions: Must handle large datasets efficiently, provide smooth scrolling, implement proper image loading, maintain performance | Success: Media browsing interface is fast, intuitive, provides rich browsing experience, handles cross-server aggregation seamlessly_\n\n- [ ] 15. 实现播放控制界面\n  - File: frontend/src/components/MediaPlayer/\n  - 创建播放控制组件和进度同步\n  - 实现远程控制功能\n  - Purpose: 提供媒体播放控制界面\n  - _Leverage: WebSocket客户端, HTML5媒体API_\n  - _Requirements: Requirement 4 - 远程播放控制_\n  - _Prompt: Role: Frontend Real-time Developer with WebSocket and media playback expertise | Task: Create media player controls with remote playback commands, progress synchronization, and device management following Requirement 4, using WebSocket for real-time communication | Restrictions: Must handle real-time updates properly, maintain playback state, support multiple devices, handle network interruptions | Success: Playback controls are responsive, sync accurately across devices, handle network issues gracefully_\n\n- [ ] 16. 创建设备管理界面\n  - File: frontend/src/views/devices/\n  - 实现设备列表、状态监控、会话管理\n  - 添加设备详情和操作历史\n  - Purpose: 提供设备监控管理界面\n  - _Leverage: 实时数据展示组件, 状态指示器_\n  - _Requirements: Requirement 5 - 设备管理和状态监控_\n  - _Prompt: Role: Frontend Monitoring Interface Developer with real-time data visualization expertise | Task: Create device management interface with device listing, status monitoring, session management, and operational history following Requirement 5, using real-time data components | Restrictions: Must handle real-time updates efficiently, provide clear status indicators, support device actions, maintain performance | Success: Device management interface provides comprehensive monitoring, handles real-time updates smoothly, supports all device operations_\n\n- [ ] 17. 完善仪表板和设置界面\n  - File: frontend/src/views/Dashboard.vue, frontend/src/views/settings/\n  - 创建综合仪表板和系统设置\n  - 添加统计图表和系统信息\n  - Purpose: 提供系统概览和配置界面\n  - _Leverage: 图表组件, 配置表单_\n  - _Requirements: 系统概览和配置需求_\n  - _Prompt: Role: Frontend Dashboard Architect with analytics and configuration interface expertise | Task: Create comprehensive dashboard with statistics, system overview, and settings interface supporting all platform configuration options | Restrictions: Must present data clearly, support various chart types, handle configuration validation, ensure settings persistence | Success: Dashboard provides valuable insights, settings interface is comprehensive and user-friendly_\n\n## 集成和部署任务\n\n- [ ] 18. 创建Docker生产配置\n  - File: docker-compose.prod.yml, Dockerfile\n  - 优化容器镜像和构建过程\n  - 配置生产环境变量和安全\n  - Purpose: 提供生产级部署配置\n  - _Leverage: 现有Docker配置, 多阶段构建_\n  - _Requirements: Requirement 6 - 系统配置和部署_\n  - _Prompt: Role: DevOps Engineer with Docker and containerization expertise | Task: Create production-ready Docker configuration with optimized images, multi-stage builds, security hardening, and deployment automation following Requirement 6 | Restrictions: Must minimize image size, implement security best practices, support multiple environments, enable monitoring and logging | Success: Production Docker configuration is secure, efficient, and deployment-ready_\n\n- [ ] 19. 创建Kubernetes部署配置\n  - File: k8s/\n  - 配置K8s部署、服务、网络\n  - 添加监控、日志、扩缩容配置\n  - Purpose: 提供企业级K8s部署方案\n  - _Leverage: Helm Charts, Kubernetes最佳实践_\n  - _Requirements: Requirement 6 - 系统配置和部署_\n  - _Prompt: Role: Kubernetes Engineer with production deployment expertise | Task: Create comprehensive Kubernetes deployment with services, ingress, monitoring, logging, and auto-scaling following Requirement 6, using Helm and K8s best practices | Restrictions: Must follow K8s patterns, implement proper resource limits, support rolling updates, ensure high availability | Success: K8s deployment is production-ready, scalable, and maintainable_\n\n- [ ] 20. 添加监控和日志系统\n  - File: monitoring/, logging/\n  - 集成Prometheus监控和Grafana可视化\n  - 配置ELK日志收集和分析\n  - Purpose: 提供系统监控和日志分析\n  - _Leverage: 现有日志系统, 监控最佳实践_\n  - _Requirements: 系统监控和运维需求_\n  - _Prompt: Role: Observability Engineer with Prometheus, Grafana, and ELK stack expertise | Task: Implement comprehensive monitoring and logging system with metrics collection, visualization, alerting, and log analysis | Restrictions: Must minimize performance impact, provide meaningful metrics, enable efficient troubleshooting, support scaling | Success: Monitoring system provides complete visibility, logging enables effective debugging, alerting is timely and accurate_\n\n- [ ] 21. 编写完整的测试套件\n  - File: tests/\n  - 实现单元测试、集成测试、E2E测试\n  - 配置CI/CD自动化测试流程\n  - Purpose: 确保系统质量和可靠性\n  - _Leverage: 现有测试框架, 自动化工具_\n  - _Requirements: 所有需求的质量保证_\n  - _Prompt: Role: QA Automation Engineer with comprehensive testing expertise | Task: Create complete testing suite including unit tests, integration tests, and E2E tests covering all platform functionality with CI/CD automation | Restrictions: Must achieve good coverage, test real scenarios, maintain test reliability, enable continuous integration | Success: Test suite is comprehensive, reliable, and provides confidence in system quality_\n\n- [ ] 22. 完善文档和部署指南\n  - File: docs/\n  - 编写用户手册、API文档、部署指南\n  - 创建故障排除和维护指南\n  - Purpose: 提供完整的项目文档\n  - _Leverage: 现有README和技术文档_\n  - _Requirements: 项目交付和维护支持_\n  - _Prompt: Role: Technical Writer with software documentation expertise | Task: Create comprehensive documentation including user guides, API references, deployment instructions, and maintenance procedures | Restrictions: Must be accurate, comprehensive, easy to follow, maintain currency with code changes | Success: Documentation enables successful deployment, usage, and maintenance of the platform_",
  "fileStats": {
    "size": 19056,
    "lines": 205,
    "lastModified": "2025-11-05T18:12:06.668Z"
  },
  "comments": []
}